winch/__init__.py
winch-0.1.0.dist-info/METADATA
winch-0.1.0.dist-info/WHEEL
winch-0.1.0.dist-info/RECORD
