Metadata-Version: 2.4
Name: winch
Version: 0.1.0
Summary: REST and RPC connection toolkit
Project-URL: Homepage, https://github.com/trankov/winch
Project-URL: Repository, https://github.com/trankov/winch
Author: Trankov
Keywords: networking,rest,rpc,toolkit
Classifier: Development Status :: 3 - Alpha
Classifier: Intended Audience :: Developers
Classifier: Programming Language :: Python
Classifier: Programming Language :: Python :: 3
Classifier: Programming Language :: Python :: 3 :: Only
Classifier: Topic :: Software Development :: Libraries
Requires-Python: >=3.14
